odoo/addons/stock_scrap_tier_validation_mrp/README.rst
odoo/addons/stock_scrap_tier_validation_mrp/__init__.py
odoo/addons/stock_scrap_tier_validation_mrp/__manifest__.py
odoo/addons/stock_scrap_tier_validation_mrp/i18n/it.po
odoo/addons/stock_scrap_tier_validation_mrp/i18n/stock_scrap_tier_validation_mrp.pot
odoo/addons/stock_scrap_tier_validation_mrp/models/__init__.py
odoo/addons/stock_scrap_tier_validation_mrp/models/mrp_production.py
odoo/addons/stock_scrap_tier_validation_mrp/models/mrp_workorder.py
odoo/addons/stock_scrap_tier_validation_mrp/readme/CONTRIBUTORS.md
odoo/addons/stock_scrap_tier_validation_mrp/readme/DESCRIPTION.md
odoo/addons/stock_scrap_tier_validation_mrp/static/description/icon.png
odoo/addons/stock_scrap_tier_validation_mrp/static/description/index.html
odoo/addons/stock_scrap_tier_validation_mrp/tests/__init__.py
odoo/addons/stock_scrap_tier_validation_mrp/tests/test_stock_scrap_tier_validation_mrp.py
odoo_addon_stock_scrap_tier_validation_mrp-17.0.1.0.0.4.dist-info/METADATA
odoo_addon_stock_scrap_tier_validation_mrp-17.0.1.0.0.4.dist-info/WHEEL
odoo_addon_stock_scrap_tier_validation_mrp-17.0.1.0.0.4.dist-info/top_level.txt
odoo_addon_stock_scrap_tier_validation_mrp-17.0.1.0.0.4.dist-info/RECORD
